{
  "lastUpdated": "2026-06-07T10:44:00.250Z",
  "totalUnique": 2200,
  "totalOccurrences": 5219,
  "filesProcessed": 8,
  "professors": [
    "Aaron Ali Lozano Rocha",
    "Aaron Ernesto Contreras Roque",
    "Aaron Mauricio Gómez Jiménez",
    "Aarón Aparicio Hernández",
    "Aarón Cruz Ramírez",
    "Abel Mosqueda Suberza",
    "Abelardo Vela Ponce de León",
    "Abraham Aldair Alvarez Galicia",
    "Abraham Kobelkowsky Díaz",
    "Abraham Lima Buendia",
    "Abril Navarrete Mena",
    "Adad Israel Gonzalez Castro",
    "Adolfo Andrade Cetto",
    "Adolfo Ernesto Cordero Borboa",
    "Adolfo Guillot Santiago",
    "Adriana Alejandra Mendoza Amador",
    "Adriana Alfaro Rosado",
    "Adriana Andraca Gómez",
    "Adriana Cruz Mejía",
    "Adriana Del Perpetuo Socorro Bravo Williams",
    "Adriana García Alarcón",
    "Adriana Gaytán Caballero",
    "Adriana Judith Xóchitl González Hernández",
    "Adriana León Montes",
    "Adriana Muñoz Hernández",
    "Adriana Patricia López Oliver",
    "Adriana Ramírez Vigueras",
    "Adriana Vargas Quintero",
    "Adriana Yanet Miranda Martínez",
    "Adriano Valdés Gómez",
    "Adrián Felipe Fernández Romero",
    "Adrián Girard Islas",
    "Adrián Martín Cruz Delgado",
    "Adrián Moisés Percastegui Rojas",
    "Adrián Téllez Mora",
    "Adrián Ulises Soto Bañuelos",
    "Adrián Zenteno Gutiérrez",
    "Adán González Andrade",
    "Adán Israel Espinosa de la Cruz",
    "Agapcel Felipe Martínez Rodríguez",
    "Agustín Carmona Castro",
    "Agustín Peralta Cuéllar",
    "Aimee Michelle Gómez Arista",
    "Aitor Lander De Icaza Astiz",
    "Aketzalli González Santiago",
    "Akshana Parameswaran Sreekala",
    "Alan Alexis Martínez López",
    "Alan Jahir Gómez Sánchez",
    "Alan Nagaya Hernández",
    "Alan Riva Palacio Cohen",
    "Alberto Alanis Pavón",
    "Alberto Alcalá Álvarez",
    "Alberto Alonso y Coria",
    "Alberto Daney Ibarra Chávez",
    "Alberto Flores Navarro",
    "Alberto González Padilla",
    "Alberto Lazcano García",
    "Alberto Manuel Aldama Garisoain",
    "Alberto Rosales Pérez",
    "Alberto Vladimir Cachón Guillén",
    "Aldair Reyes González",
    "Aldo César Almazán Avilés",
    "Aldo Domínguez de la Torre",
    "Aldo Espinosa Sosa",
    "Aldo Martínez Campos",
    "Alejandra Abigail González Valdez",
    "Alejandra Barrios Flores",
    "Alejandra Carolina Barrios Barocio",
    "Alejandra Concepción Aguirre Zavaleta",
    "Alejandra García García",
    "Alejandra López Suárez",
    "Alejandra Mireles Vázquez",
    "Alejandro Aldama Cervantes",
    "Alejandro Alvarado Corzo",
    "Alejandro Alvarado García",
    "Alejandro Argudín Monroy",
    "Alejandro Bautista Orozco",
    "Alejandro Cristin Ponciano",
    "Alejandro Cruz Vázquez",
    "Alejandro Córdoba Aguilar",
    "Alejandro De Las Peñas Castaño",
    "Alejandro Esparza García",
    "Alejandro Estradas Romero",
    "Alejandro Felipe Zarate Pérez",
    "Alejandro Gaona Ordóñez",
    "Alejandro Gurrola Luna",
    "Alejandro Hérnandez Cuevas",
    "Alejandro Jacome Delgado",
    "Alejandro Legaspe Serrano",
    "Alejandro Piña Vargas",
    "Alejandro Ramírez Buenrostro",
    "Alejandro Reyes Coronado",
    "Alejandro Rodrigo Jácome Ramírez",
    "Alejandro Ríos Herrejón",
    "Alejandro Schmidt Ruíz del Moral",
    "Alejandro Sánchez Cervantes",
    "Alejandro Villarreal López",
    "Alejandro Vásquez Arzola",
    "Alette Ortega Gómez",
    "Alexander José López Ruíz",
    "Alexander Llanes Quevedo",
    "Alexander Pérez Degante",
    "Alexander Valladares Mc Nelis",
    "Alexandra Guzmán Velázquez",
    "Alexis Eduardo López Velázquez",
    "Alexis Wences Cortés",
    "Alfonso Montañez Arce",
    "Alfonso Ortiz Avila",
    "Alfonso Zavala Cessa",
    "Alfredo Eduardo Flores Serrano",
    "Alfredo Juan Arnaud Bobadilla",
    "Alfredo López Castillo",
    "Ali Fransuani Jiménez González",
    "Alicia Callejas Chavero",
    "Alicia Cruz Martínez",
    "Alicia Enriqueta Brechú Franco",
    "Alicia Margarita de la Mora Cebada",
    "Alicia María Oliver y Gutiérrez",
    "Alicia Negrón Mendoza",
    "Alicia Rojas Ascencio",
    "Alin Patricia Acuña Alonzo",
    "Alipio Gustavo Calles Martínez",
    "Alma Lilia Álvarez Guerrero",
    "Alma Liliana Huerta Ornelas",
    "Alma Melisa Vázquez López",
    "Alma Rosa Bustamante García",
    "Alma Saraí Hernández Torres",
    "Alma Valeria Velarde Ortega",
    "Alma Violeta García López",
    "Alma Virgen Mendoza Ponce",
    "Alondra Aguilar Lopez",
    "Alonso Alejandro Colín Cruz",
    "Alonso Martínez Canabal",
    "Alvaro Daniel Cruz Cortes",
    "Alya Ramos Ramos Elorduy",
    "Amadeo Luis Estrada Nieto",
    "Amaranta Ramírez Terrazo",
    "Amparo López Gaona",
    "Amy Megan Chávez Montejano",
    "América Vanoye Carlo",
    "Amílcar José Escobedo Pérez",
    "Ana Cecilia Noguez Garrido",
    "Ana Cecilia Rocher Maliachi",
    "Ana Cristina Cervantes Arrioja",
    "Ana Gabriela Flores Delgado",
    "Ana Gabriela Hernández Ochoa",
    "Ana Laura Colín González",
    "Ana Laura Córdova Lara",
    "Ana Laura Trujillo Negrete",
    "Ana Lilia Anaya Muñoz",
    "Ana Lilia Hernández Damián",
    "Ana Lilia Juárez Vázquez",
    "Ana Lucía Sereno Uribe",
    "Ana Margarita Hermoso Salazar",
    "Ana María Beatriz Cetto Kramis",
    "Ana María Soler Arechalde",
    "Ana Meda Guardiola",
    "Ana Pamela Gutiérrez Martínez",
    "Ana Sofía Pineda Rios",
    "Ana Valeria Beltrán Sánchez",
    "Ana Valeria Martínez Silva",
    "Anabel Jáuregui Hernández",
    "Anabel Mitjans Alayon",
    "Analia Pérez Roman",
    "Anatolio Hernández Quintero",
    "Anayanzi Delia Martínez Hernández",
    "Anays Acevedo Barrera",
    "Andrea Alejandra Caballero Ochoa",
    "Andrea Avilez Ortega",
    "Andrea Burgos Cuevas",
    "Andrea González Isidoro",
    "Andrea Luisa Aburto Espina",
    "Andrea Sabido Ramos",
    "Andrea Sanjuan Badillo",
    "Andrea Sofía Ceñal Cisneros",
    "Andrea Valdés Hernández",
    "André Sebastián García Ward",
    "Andrés Abraham Álvarez Pérez",
    "Andrés Alonso Flores Marín",
    "Andrés Camacho López",
    "Andrés Carnero Bravo",
    "Andrés Eduardo Medrano Albarrán",
    "Andrés Jiménez Lizárraga",
    "Andrés Oswaldo Rivera Hernández",
    "Andy Dorey Ruiz Huerta",
    "Angel Armando Moreno Ortega",
    "Angel Cuevas Romero",
    "Angel Domingo Gallegos Pazos",
    "Angel Eduardo Herrera Mares",
    "Angel Ignacio Iván Huerta Monzalvo",
    "Angel Israel Ortega Pazos",
    "Angel Rodrigo González González",
    "Angela Arango Galván",
    "Angela Lemus Torres",
    "Angela Zugeily Segura Lucas",
    "Angélica Carrillo Verduzco",
    "Angélica Monserrat Rubio Vega",
    "Angélica Tapia Pazos",
    "Antonio Camacho Carrera",
    "Antonio Carrillo Ledesma",
    "Antonio Cruz Peralta",
    "Antonio García Flores",
    "Antonio Maximiliano Ortíz Rodríguez",
    "Antonio Romero Téllez",
    "Antonio Ruiz Morán",
    "Antonio Soriano Flores",
    "Antonio Vázquez Bertran",
    "Antonio Yairt Mejía Millán",
    "Antonio Yolocalli Cisneros Bernal",
    "Araceli Eugenia Mercado Fernández",
    "Araceli García Flores",
    "Araceli Liliana Reyes Cabello",
    "Araceli Ortega Díaz",
    "Aramis Arias Romero",
    "Araxi Urrutia Odabachian",
    "Arcadio Huerta Hernández",
    "Areli Elizabeth González Mendoza",
    "Areli Huanosta Gutiérrez",
    "Ariadna Olvera Sampieri",
    "Ariadna Valeria Paredes Daza",
    "Ariana Zavala Moreno",
    "Arianee Sainz Vidal",
    "Ariel Adara Mercado Martínez",
    "Ariel Alberto Valladares Clemente",
    "Arilín Susana Haro Palma",
    "Armando Antillón Díaz",
    "Armando Sosa Yañez",
    "Artico Ramírez Urrutia",
    "Arturo Carlos II Becerra Bracho",
    "Arturo Carranza Melgarejo",
    "Arturo Cortés Islas",
    "Arturo Espinosa Vargas",
    "Arturo García Gómez",
    "Arturo López González",
    "Arturo Misael Reyes Colín",
    "Arturo Molina Valle",
    "Arturo Olvera Vital",
    "Arturo Rodríguez Gómez",
    "Arturo Sajid García Velasco",
    "Arturo Tinoco Arenas",
    "Ashok Adhikari",
    "Ateet Dutt",
    "Athziri Hernández Jiménez",
    "Atzi Merino",
    "Augusto Cabrera Becerril",
    "Augusto César Poot Hernández",
    "Augusto José González Canto",
    "Aurea Espinosa Cerón",
    "Aurora Georgina Bustos Arellano",
    "Aurora Marrón Becerra",
    "Aurore Marie Pascale Nicole Courtoy",
    "Axel Ricardo De la Macorra Pettersson Moriel",
    "Axel Sael Blanco Olivares",
    "Beatriz Brito Martínez",
    "Beatriz Irene Lira Hernández",
    "Beatriz Zúñiga Ruiz",
    "Beatríz Santiago Ramírez",
    "Belen Cruz Montoya",
    "Belén Espinosa Lucio",
    "Benito Juárez García",
    "Benjamin Castillo Monterrosas",
    "Benjamín Cristian Corona Comunidad",
    "Benjamín Figueroa Solano",
    "Benjamín Oliva Vázquez",
    "Benjamín Pablo Norman",
    "Benjamín Sánchez Hernández",
    "Benjamín Valencia Nieto",
    "Berenice García Ponce de León",
    "Berenice Martínez Barona",
    "Berenice Márquez Valadez",
    "Bernardo Carranza Becerra",
    "Bertha Molina Alvarez",
    "Bertha Molina Brito",
    "Bertha Verónica Valverde Garduño",
    "Betsy Anaid Peña Ocaña",
    "Bianca Julieta Vizcarra Chacón",
    "Bibiana Obregón Quintana",
    "Blanca Dulce Miriam Benítez Pérez",
    "Blanca Estela Hernández Baños",
    "Brandon Alejandro Reyes Ferrer",
    "Brandon Bustos García",
    "Braulio Osvaldo Alzate Chacón",
    "Brayan Matias Rojo",
    "Brenda Abril Néquiz Guillén",
    "Brenda Anabel López Ruiz",
    "Brenda Ayala Flores",
    "Brenda Elías Sánchez",
    "Brenda Ixcuiname Saavedra Reyes",
    "Brenda Karytza Montiel Ramírez",
    "Brenda Lizeth Ramírez Arista",
    "Brenda Margarita Becerra Ruíz",
    "Brenda Martínez Velasco",
    "Brian Urbano Alonso",
    "Brian del Angel Becerra Bressant",
    "Brisa Lizeth Arenas Gómez",
    "Briseida Guadalupe Pérez Hernández",
    "Briseida Guadalupe Trejo Escamilla",
    "Bruno Arturo Barrales Alcalá",
    "Bruno Manuel Chávez Vergara",
    "Bryan Enrique Pérez Cervantes",
    "Bryant Canseco Hernández",
    "Bárbara Pamela Serrano Flores",
    "Cain Arturo Díaz Huerta",
    "Camila Itzel Marín Gómez",
    "Camilo José Medina Ramírez",
    "Canek Peláez Valdés",
    "Carisa Cano Figueroa",
    "Carl Michael Sune Reimer López",
    "Carlos Abraham Ochoa Moya",
    "Carlos Alberto Durán Ramírez",
    "Carlos Alberto Ochoa Olmos",
    "Carlos Alberto Peralta Alvarez",
    "Carlos Alberto Vital José",
    "Carlos Alfredo Norzagaray Márquez",
    "Carlos Alfredo Silva Islas",
    "Carlos Andrés Gil Gómez",
    "Carlos Contreras Cruz",
    "Carlos Daniel Tamayo Castro",
    "Carlos Daniel Velázquez Mendoza",
    "Carlos David Jiménez Flores",
    "Carlos Echeverría Arjonilla",
    "Carlos Eduardo Martínez Aguilar",
    "Carlos Enrique Román Velázquez",
    "Carlos Federico Bunge Molina",
    "Carlos Fernando Vásquez Guerra",
    "Carlos Francisco Betancourt Moreno",
    "Carlos Gerardo Acosta Hernández",
    "Carlos Gerardo Paniagua Ramírez",
    "Carlos Granados Peláez",
    "Carlos Islas Moreno",
    "Carlos Israel Román Aguilera",
    "Carlos Iván Falcón Rodríguez",
    "Carlos Iván Lingan Pérez",
    "Carlos Javier Cureño Ayluardo",
    "Carlos Javier Villagómez Ojeda",
    "Carlos Jesús Román Moreno",
    "Carlos José Cabrera Muñoz",
    "Carlos Moisés Arriaga Osante",
    "Carlos Málaga Iguiñiz",
    "Carlos Omar Castañeda Díaz",
    "Carlos Orozco Rocha",
    "Carlos Polanco González",
    "Carlos Prieto López",
    "Carlos Ramírez Ramos",
    "Carlos Reyes Damián",
    "Carlos Rodolfo Barrera Anzaldo",
    "Carlos Torres Alcaraz",
    "Carlos Zerón Martínez",
    "Carlos Álvarez Jiménez",
    "Carmen Daniela Acevedo Arellano",
    "Carmen Grisel Méndez García",
    "Carmen Lucia Bustillo Hernández",
    "Carmen Martínez Adame Isais",
    "Carolina Rivera Arredondo",
    "Carolina Rodríguez Ibarra",
    "Carolina Sánchez García",
    "Castor Mauricio Rueda García",
    "Catalina Elizabeth Stern Forgach",
    "Cecilia Amparo García Sánchez",
    "Cecilia Chávez Aguilera",
    "Celia Esperanza Sanginés Franco",
    "Cesar Valdovinos Flores",
    "Christian Alfredo Solís Calderón",
    "Christian Gabriel Miranda Ruíz",
    "Christopher Jonay Muñoz Flores",
    "Christopher Villagra Piña",
    "Chumin Wang Chen",
    "Cinthia Carina Lázaro Paz",
    "Cinthia Rocío Juárez Tapia",
    "Cinthya Mendoza Almeralla",
    "Citlali Sánchez Aké",
    "Citlali Yuriria Núñez Mariel",
    "Citlalli Mendez Ramos",
    "Claudia Adriana Colín Castro",
    "Claudia América Serrano Liceaga",
    "Claudia Andrea Segal Kischinevzky",
    "Claudia Elena Guadalupe Palacios Macías",
    "Claudia Elizabeth Peña Mata",
    "Claudia Elizabeth Ruiz Rodríguez",
    "Claudia Itzel Pedraza Acevedo",
    "Claudia Karina Torres Villaseñor",
    "Claudia Olivera Tlahuel",
    "Claudia Orquídea López Soto",
    "Claudia Solís Said",
    "Claudia Sánchez Cárdenas",
    "Claudia Velázquez Cervantes",
    "Claudia Villegas Azcorra",
    "Claudia Yali Tello Hérnandez",
    "Claudio Francisco Nebbia Rubio",
    "Claudio Narciso Ramírez",
    "Clementina de los Ángeles Equihua Zamora",
    "Clotilde García Villa",
    "Coral Cruz González Luna",
    "Corina Solís Rosales",
    "Crescencio García Segundo",
    "Cristian Adán Mojica Casique",
    "Cristian Axel Muñoz Flores",
    "Cristian Cornejo Latorre",
    "Cristian Cuevas Morales",
    "Cristian Edimar Morales Encinos",
    "Cristian Felipe Cruz García",
    "Cristian Joel Osorio Mancipe",
    "Cristian Josué Núñez Serna",
    "Cristina Angélica Núñez Rodríguez",
    "Cristina Isabel Guzmán Gónzalez",
    "Cristina Jasso Del Toro",
    "Cristina Nieto Vasconcelos",
    "Cristobal Falconi Hoyos",
    "Cristopher Alejandro Escamilla Soto",
    "Cuauhtémoc Ramírez Pimentel",
    "Cynthia Fernández Lainez",
    "Cynthia Lizbeth Sánchez Urbano",
    "César Adrián González Martínez",
    "César Alberto Aguillon Barrera",
    "César Alberto Díaz Hérnandez",
    "César Antonio Ortiz Martínez",
    "César Antonio Ríos Muñoz",
    "César Augusto Aguilar Martínez",
    "César Augusto Domínguez Pérez-Tejada",
    "César Augusto Santamaría Vergara",
    "César Daniel Alejándrez García",
    "César Eduardo Jardines Mendoza",
    "César Eduardo Sousa Mondragón",
    "César Enrique Terán Cisneros",
    "César Garnica Navarro",
    "César Hernández Cruz",
    "César Ismael Corral Rojas",
    "César Leonardo Ordóñez Romero",
    "César Noé Cortés Rubio",
    "César Oliver Lara Figueroa",
    "César Owen González Guerrero",
    "César Rodrigo Calderón Villegas",
    "Dafne Estefany Bonilla Cerquedo",
    "Dahi Ludim Hernández Roa",
    "Dailer Rolando Fontisiella Morell",
    "Dalia García Alcántara",
    "Dalila Fragoso Tejas",
    "Damián Real Corrales",
    "Dana Larissa Luna González",
    "Danaí Montalván Sorrosa",
    "Dania Sayuri Zaldívar Tanaka",
    "Daniel Alejandro Olvera Sule",
    "Daniel Alfredo García Sánchez",
    "Daniel Armando Pérez Calderón",
    "Daniel Balam Cruz Huitrón",
    "Daniel Cervantes Filoteo",
    "Daniel Edwin Domínguez León",
    "Daniel Espinosa González",
    "Daniel José Marín Lámbarri",
    "Daniel Kosoi La Mont",
    "Daniel León Álvarez",
    "Daniel Michel Tavera",
    "Daniel Montana Estudillo Hernández",
    "Daniel Moreno Vázquez",
    "Daniel Murguia Luciano",
    "Daniel Navarro Santillán",
    "Daniel Ochoa Gutiérrez",
    "Daniel Ortega Laureles",
    "Daniel Pulido Arévalo",
    "Daniel Pérez Calixto",
    "Daniel Rivera Mendoza",
    "Daniel Rojas Hérnandez",
    "Daniel Rojo Mata",
    "Daniel Ruelas Milanés",
    "Daniel Winney Corona",
    "Daniel Ávila Hernández",
    "Daniela Abigail Guzmán Ramírez",
    "Daniela Alejandra Estrada Molina",
    "Daniela Alejandra González Ramírez",
    "Daniela Colmenares Sierra",
    "Daniela Mariyet Terán Guerrero",
    "Daniela Patricia Morales Velarde",
    "Daniela Paulina Heredia Jiménez",
    "Daniela Tapia Magaña",
    "Daniela Thalia Candia Ramírez",
    "Daniela Ávila González",
    "Dario Emmanuel Vázquez Ceballos",
    "Darío Núñez Zúñiga",
    "Darío Rigoberto Rivera Calzadilla",
    "David Alberto Fariña Ochoa",
    "David Alejandro Aquino Garcia",
    "David Angel de Jesus Luna",
    "David Armando Silva de Paz",
    "David Bañuelos Solórzano",
    "David Garciadiego Cázares",
    "David Hernández Obin",
    "David Hinojosa Romero",
    "David José Zamudio Ángeles",
    "David Ley Domínguez",
    "David Melquiades Medina Pérez",
    "David Meza Alcántara",
    "David Ortega Medina",
    "David Parra Guevara",
    "David Porta Zepeda",
    "David Salinas Torres",
    "David Xochipiltecatl García",
    "Dayana Claudia Cruz Delgado",
    "Deborah Veranea Espinosa Martínez",
    "Delia Iresine Bello Segura",
    "Denisse Ariadna Gutiérrez Rojas",
    "Dennis Itzel Martínez Moreno",
    "Deyanira Pérez Morales",
    "Diana Alethia Guerrero Hernández",
    "Diana Avella Alaminos",
    "Diana Catalina Castro Rodríguez",
    "Diana Courcelle Chaparro",
    "Diana Itzel Flores Baeza",
    "Diana Itzel Páez Sánchez",
    "Diana Nahidally Martínez García",
    "Diana Paola Méndez Hernández",
    "Diana Pardo De la Rosa",
    "Diana Patricia Rosales Cruz",
    "Diana Perez Xicohtencatl",
    "Diana Pineda Vázquez",
    "Diana Romo Carrillo",
    "Diana Soriano Fernández",
    "Diana Verónica Domínguez González",
    "Diana Yareth Santoya Ugalde",
    "Dianadalia Bernal González",
    "Diego Acosta Tovar",
    "Diego Alberto Carrasco Morán",
    "Diego Alejandro Iniesta Miranda",
    "Diego Alejandro Velázquez Cervantes",
    "Diego Alexander Ramirez Angarita",
    "Diego Antonio Villalba González",
    "Diego Armando Esquivel Hernández",
    "Diego Daniel González Araiza",
    "Diego Dozal Magnani",
    "Diego Eugenio Vallejo Carpintero",
    "Diego Fenoglio Huergo",
    "Diego García Meza",
    "Diego López Cámara Ramírez",
    "Diego Mauricio Gómez Coral",
    "Diego Méndez Medina",
    "Diego Yahir Barrueta Morán",
    "Dilan Aldair Rubi Soberanes",
    "Diosel López Cruz",
    "Donají Xóchitl Cruz López",
    "Donovan Eduardo Calva Caggiano",
    "Donovan Kevin Gálvez Márquez",
    "Doroteo Mendoza López",
    "Dulce Angélica Zugasti Fernández",
    "Dulce Jocelyn Bustamante Valdez",
    "Dulce Yehimi López Miranda",
    "Edgar Aaron Rosales Santiago",
    "Edgar Adán Jiménez Díaz",
    "Edgar Alvarez Zauco",
    "Edgar Colín Cruz",
    "Edgar Gasperín García",
    "Edgar Gerardo Alarcón González",
    "Edgar Gil Hernández Díaz",
    "Edgar Israel Fuentes Oliver",
    "Edgar Migueles Pérez",
    "Edgar Mixcoha Hernández",
    "Edgar Omar Torres Álvarez",
    "Edgar Omar Velasco Páez",
    "Edgar Orlando Ramírez Castro",
    "Edgar Pastrana Calderón",
    "Edgar Rangel Barrios",
    "Edgar Vargas Solís",
    "Edgar Vázquez Luis",
    "Edgar Yael Marbán Pérez",
    "Edgardo Galán Vásquez",
    "Edith Auryn Téllez Guzmán",
    "Edith Corina Sáenz Valadez",
    "Edna Arévalo Marín",
    "Edna Dennise Gómez González",
    "Edna Magdalena Hernández González",
    "Edson André Cortés Silva",
    "Eduardo Alberto Pérez García",
    "Eduardo Andrade Ibarra",
    "Eduardo Augusto Ferreriz Duarte",
    "Eduardo Bello Castañeda",
    "Eduardo Everardo García Cárdenas",
    "Eduardo Hernández Hernández",
    "Eduardo Jacobo Villegas",
    "Eduardo José Vega Murguía",
    "Eduardo León Rodríguez",
    "Eduardo Lince Gómez",
    "Eduardo López Lima",
    "Eduardo Morales Gamboa",
    "Eduardo Morales Guillaumin",
    "Eduardo Peinado Rodríguez",
    "Eduardo Rangel Cortés",
    "Eduardo Selim Martínez Mayorga",
    "Eduardo Tonathiu López Morales",
    "Eduardo Torres Flores",
    "Eduardo Torres Luna",
    "Edward Daniel Reyes Ramírez",
    "Edwin Aldrin Juárez Aguilar",
    "Edwin Antonio Galván Gámez",
    "Edwin Giovany Rebollar Madariaga",
    "Edén Marcela Rodríguez Flores",
    "Efraín Ossmar Díaz Pérez",
    "Efraín Rafael Chávez Lomelí",
    "Eleazar Cuautle Flores",
    "Eleazar Neri Medina",
    "Elena de Oteyza de Oteyza",
    "Elhoim Llorente Sumano y Ramírez",
    "Elia Lemus Santana",
    "Elia Matias Hernández",
    "Elia Ramírez Arriaga",
    "Elie Macario Peña Ruiz",
    "Elisa Sugey Hernández Castañeda",
    "Elisana Perea Romero",
    "Elizabeth Chalnique Ríos Alvarado",
    "Elizabeth Damayanthi López Márquez",
    "Elizabeth Eugenia Téllez Ballesteros",
    "Elizabeth Padilla Rodal",
    "Elmer Enrique Tovar Acosta",
    "Elsa Guadalupe Escamilla Chimal",
    "Elsa Patricia Mendoza Ballesteros",
    "Elsa Puente Vázquez",
    "Elva Bazán Mora",
    "Elvia María Ramírez Carrillo",
    "Elías Okón Gurvich",
    "Emiliano García Vázquez",
    "Emiliano García Ávila",
    "Emiliano Geneyro Squarzon",
    "Emiliano Hernández Salazar",
    "Emiliano Rodrigo Arroyo Sánchez",
    "Emilio Cabrera Castro",
    "Emilio Espinoza Simón",
    "Emilio Esteban Lluis Puebla",
    "Emma Cecilia Saavedra Lira",
    "Emma Cristina López Hernández",
    "Emma Lam Osnaya",
    "Emma Laura Guzman Garcia",
    "Emmanuel David Silva Amaya",
    "Emmanuel Ismael González Celio",
    "Emmanuel Moreno López",
    "Emmanuel Segura Pérez",
    "Enikar Manuel Morales Patlán",
    "Enoc Pineda Aguirre",
    "Enrique Ehecatl Hernández Ferreiro",
    "Enrique Francisco Soto Astorga",
    "Enrique Guillermo Bazúa Durán",
    "Enrique Hernández Hernández",
    "Enrique Javier Elizondo Huerta",
    "Enrique López Moreno",
    "Enrique Macario Herrera Medina",
    "Enrique Maturano Rodríguez",
    "Enrique Moreno Méndez",
    "Enrique Moreno Sáenz",
    "Enrique Ortiz Bermúdez",
    "Enrique Sahid Tenorio Rodríguez",
    "Enrique Vega Castillo",
    "Enrique Vega Ramírez",
    "Enrique Álvarez del Castillo de Pina",
    "Erandi Tzayani Rodríguez Pérez",
    "Erasmo Catarino Ávila Mendoza",
    "Eric Daniel Hernández Jardón",
    "Eric Flores Hernández",
    "Eric Garcia Bustamante",
    "Eric Sebastián Sánchez Conde",
    "Eric Toporek Coca",
    "Eric Vázquez Jáuregui",
    "Erick Alejandro García Trejo",
    "Erick Barrios Barocio",
    "Erick Eduardo Aguilar Hernández",
    "Erick Eduardo Talavera Perea",
    "Erick Emmanuel Pérez Franco",
    "Erick Fabián Pérez Léon",
    "Erick Leonardo Patiño Jaidar",
    "Erick Manuel Pineda Rios",
    "Erik Quintero Villeda",
    "Erika Mayela Ramírez Barbosa",
    "Erika Muñoz Moral",
    "Erin Christy McKiernan",
    "Ernesto Alejandro Vázquez Navarro",
    "Ernesto Cruz Guerrero",
    "Ernesto Gustavo Tovar Bustamante",
    "Ernesto López Cacho",
    "Ernesto Mayorga Saucedo",
    "Ernesto Rivera García",
    "Ernesto Rosales González",
    "Ernesto Rosas García",
    "Ernesto Yahir Rivera Hernández",
    "Esmeralda Lizet Martínez Piñeiro",
    "Esperanza Torres Rodríguez",
    "Esteban Librado Hernández Escamilla",
    "Esteban Rubén Hurtado Cruz",
    "Estefania Alvarez Avalos",
    "Estefania Arroyo Jilote",
    "Estela Cuna Pérez",
    "Estela Margarita Puente Leos",
    "Esther Aguilar Román",
    "Esther Zúñiga Sánchez",
    "Eugenia Marmolejo Rivas",
    "Eugenia Paola Arévalo López",
    "Eugenio Garnica Vigil",
    "Eulogia Marisol Pérez Amador",
    "Eva Aguirre Hernández",
    "Evelia Lorena Coss Navarrete",
    "Evelina Hernández Hernández",
    "Evelyn Venegas Agustín",
    "Fabio Andrés Vallejo Narváez",
    "Fabio De Colle",
    "Fabiola Elena Fortuna Montecillo",
    "Fabiola Hernández Vázquez",
    "Fabiola Ramírez Corona",
    "Fabiola Sánchez Roa",
    "Fabiola Villela Cortes",
    "Fabián Elizalde Hernández",
    "Faustino Sánchez Garduño",
    "Favio Ezequiel Miranda Perea",
    "Federico Jesús Cázarez Bush",
    "Federico Ricalde Sánchez",
    "Federico Sánchez Bringas",
    "Felipe Angeles García",
    "Felipe Campos Cerda",
    "Felipe Hernández Lorenzana",
    "Felipe Zamora Ramos",
    "Felipe de Jesús Eslava Silva",
    "Felisa Josefina Aguilar Arellano",
    "Felix Krengel",
    "Fernanda Aide Arreola Luna",
    "Fernando Alvarez Padilla",
    "Fernando Baltazar Larios",
    "Fernando Brambila Paz",
    "Fernando Camacho Rico",
    "Fernando Díaz López",
    "Fernando Esteban Contreras Mendoza",
    "Fernando García García",
    "Fernando Guerrero Poblete",
    "Fernando Javier Nuñez Rosales",
    "Fernando Jesús Méndez de la Cruz",
    "Fernando Josue Reyes Ortega",
    "Fernando Michel Tavera",
    "Fernando Núñez Useche",
    "Fernando Ramírez Martínez",
    "Fernando René Martínez Ortiz",
    "Fernando Rojas Linares",
    "Fernando Sánchez Castillo",
    "Fernando Sánchez Rueda",
    "Fernando Velázquez Carreón",
    "Fernando Ángeles Uribe",
    "Fidel Casarrubias Segura",
    "Fidel Roberto Castellanos Duran",
    "Fidencio Galicia Rodríguez",
    "Flor Guadalupe Haro Velazquez",
    "Francisco Angel Campos Rodríguez",
    "Francisco Arzola Galindo",
    "Francisco Giovanni López Sánchez",
    "Francisco González Montoya",
    "Francisco Javier Alvarado Cabrera",
    "Francisco Javier Bautista Clemente",
    "Francisco Javier Sevilla Pérez",
    "Francisco Javier Torres Ayala",
    "Francisco Javier Vega Vera",
    "Francisco Jose Santiago Martinez",
    "Francisco José Medina Soriano",
    "Francisco Larrión Riveroll",
    "Francisco Marmolejo Rivas",
    "Francisco Morales Leal",
    "Francisco Nettel Rueda",
    "Francisco Parraguirre Sánchez",
    "Francisco Páez Pérez",
    "Francisco Ruiz Sala",
    "Francisco Sour Tovar",
    "Francisco Sánchez Villarreal",
    "Francisco Valadez Cruz",
    "Francisco Valdés Souto",
    "Francisco de Jesús Rivera Torres",
    "Frank Patrick Murphy Hernández",
    "Freddy Jackson Poveda Cuevas",
    "Frida Michelle Vargas Bautista",
    "Fructuoso Matias García",
    "Félix Antonio Centeno Salas",
    "Félix Yael López Cayetano",
    "Gabino De la Rosa Cruz",
    "Gabriel Gutiérrez García",
    "Gabriel López Velázquez",
    "Gabriel Sinué Fonseca Salazar",
    "Gabriela Campero Arena",
    "Gabriela Cervantes Piza",
    "Gabriela Frías Villegas",
    "Gabriela García Verde",
    "Gabriela González González",
    "Gabriela Hernández Aguilar",
    "Gabriela Jacqueline Cervantes Acevedo",
    "Gabriela Meléndez Vargas",
    "Gabriela Murguía Romero",
    "Gabriela Rueda de la Cruz",
    "Gala Artemisa Viurcos Martínez",
    "Gala Cortés Ramírez",
    "Galo David Ruiz Soto",
    "Gasde Augusto Hunedy López",
    "Genaro Vázquez Victorio",
    "Georgina Jatzire Arévalo Pacheco",
    "Georgina Marisol Molina Granados",
    "Georgina Nieto Castañeda",
    "Georgina Santos Barrera",
    "Geovani Martínez Martínez",
    "Gerardo Acosta García",
    "Gerardo Avilés Rosas",
    "Gerardo Daniel Rayo López",
    "Gerardo Emiliano Figueroa Sandoval",
    "Gerardo García Naumis",
    "Gerardo Jorge Vázquez Fonseca",
    "Gerardo Juárez Flores",
    "Gerardo Mata Torres Valle",
    "Gerardo Mejía Rodríguez",
    "Gerardo Mejía Vázquez",
    "Gerardo Miguel Tecpa Galván",
    "Gerardo Ramírez Mejía",
    "Gerardo Rivas Álvarez",
    "Gerardo Ruiz Chavarría",
    "Gerardo Sánchez Licea",
    "Germán Emiliano López Fernández",
    "Germán Ernesto Zapata Ledesma",
    "Germán Fernando Gutiérrez Aguilar",
    "Gertrudis Hortensia González Gómez",
    "Gethsemany García Guerrero",
    "Gibrán Ramiro Reynoso Jiménez",
    "Gilberto Alemán Sancheschúlz",
    "Gilberto Armando Casillas Pérez",
    "Gilberto Bruno Pérez",
    "Gildardo Bautista García Cano",
    "Gilde Valeria Rodríguez Jiménez",
    "Giovani Hernández Canchola",
    "Giovanna Michelle Maldonado Maldonado",
    "Giselle Alejandra Román Chong",
    "Giuseppe Pirruccio",
    "Gonzalo Pérez de la Cruz",
    "Gonzalo Sánchez García",
    "Gonzalo Ángel Ramírez Cruz",
    "Graciela Arce Rocha",
    "Graciela Zamudio Varela",
    "Gregorio Ruiz Chavarría",
    "Griselda Adriana Cruz Priego",
    "Grissel Santiago González",
    "Guadalupe Andraca Gómez",
    "Guadalupe Geraldine González Rodríguez",
    "Guadalupe Iriliana López Caballero",
    "Guadalupe Martínez Salgado",
    "Guadalupe Vidal Gaona",
    "Guadalupe Villeda Gómez",
    "Guerda Massillon Jacques-Louis",
    "Guillermina Alcaraz Zubeldia",
    "Guillermina Cabañas Carranza",
    "Guillermo Abraham Quintana Silva",
    "Guillermo Adolfo Méndez Roche",
    "Guillermo Alberto Ramos Blancas",
    "Guillermo Enrique Hernández Sánchez",
    "Guillermo Garro Gómez",
    "Guillermo Reyes Valencia",
    "Guillermo Rolando Rosas Figueroa",
    "Guilmer Ferdinand González Flores",
    "Gustavo Adolfo Garduño Martínez",
    "Gustavo Armendariz Peña",
    "Gustavo Arturo Márquez Flores",
    "Gustavo Becerril Hernández",
    "Gustavo Carreón  Vázquez",
    "Gustavo De la Cruz Martínez",
    "Gustavo Enrique García de Jesús",
    "Gustavo Meléndez Valentin",
    "Gustavo Pacheco Santiago",
    "Gustavo Sandoval Joya",
    "Hans Cruz Prado",
    "Hansel Argyll Gordillo Ruiz",
    "Hararec Medina Gónzalez",
    "Harim García Lamont",
    "Harry Alvarez Ospina",
    "Helena Lizárraga Collí",
    "Helena Socorro Hernández Rosales",
    "Helios Farrell González",
    "Hilda Angélica Martínez Becerril",
    "Horacio Valdemar Bárcenas Rodríguez",
    "Horacio Villafán Monroy",
    "Hortensia Galeana Sánchez",
    "Hugo Alberto Lara Garcia",
    "Hugo Alberto Rincón Mejía",
    "Hugo Antonio Tovar Romero",
    "Hugo Bernardo Reséndiz García",
    "Hugo Guadalupe Reyna Castañeda",
    "Hugo Iván Cruz Rosas",
    "Hugo Martín Sobral",
    "Hugo Merlín Ramírez",
    "Hugo Rivas Martínez",
    "Hugo Torres Vargas",
    "Hugo Villaseñor Hernández",
    "Humberto Andrés Carrillo Calvet",
    "Humberto Jair Hijar Juárez",
    "Humberto Plata Gallegos",
    "Huziel Enoc Sauceda Félix",
    "Héctor Alessandro López Hernández",
    "Héctor Alfonso Malagón Rivero",
    "Héctor Alva Sánchez",
    "Héctor Bustos Castro",
    "Héctor Cruz Ramírez",
    "Héctor Daniel Alonso Orozco",
    "Héctor Domínguez Castro",
    "Héctor Fernando Carrada Rodríguez",
    "Héctor Gilberto Vázquez López",
    "Héctor Jesús Díaz Jiménez",
    "Héctor Jiménez Sánchez",
    "Héctor Manuel Hernández Toledo",
    "Héctor Martín Abundis Manzano",
    "Héctor Miguel Mejía Díaz",
    "Héctor Miguel Ortíz Rangel",
    "Héctor Méndez Lango",
    "Héctor de Jesús Cruz-Manjarrez Flores-Alonso",
    "Ian Israel García Vázquez",
    "Ignacio Arturo Quintanar Isaías",
    "Ignacio Mauro Vázquez Rojas",
    "Ileana de la Fuente Colmenares",
    "Ilhuice Nemi Alcántara Martínez",
    "Ilse Gema Peña Bernardino",
    "Ingrid Chávez Cisneros",
    "Inmaculada Concepción Expósito Cívico",
    "Irad Portocarrero González",
    "Irama Silvia Marisela Núñez Tancredi",
    "Irene Guadalupe Nava Ruíz",
    "Iris Rosario Camacho Espinoza",
    "Irlanda de Lourdes Palma y Meza Montoya",
    "Irma Rocío Villa Valles",
    "Irvin Arellano Rosas",
    "Irvin Fermín Ángeles Aguillón",
    "Irvin Javier Cruz Gónzalez",
    "Irving Daniel Calderón Camacho",
    "Irving Hernández Rosas",
    "Isaac González García",
    "Isaac Israel Hérnandez Hérnandez",
    "Isaac Muñoz Estrada",
    "Isaac Romeo Acevedo Rojas",
    "Isaac Romero Solano",
    "Isabel Catalina Barrera Díaz",
    "Isabel Espino Gutiérrez",
    "Isabel Monserrat Sánchez Barrera",
    "Isabel Vásquez Ortiz",
    "Isabel Yajaira Rojas Martinez",
    "Isabela Vivas Toro",
    "Isaías Manuel Ramírez Bañales",
    "Isaías Rodríguez Aguirre",
    "Ismael Rivera Jiménez",
    "Ismael Velázquez Gómez",
    "Israel Chávez Villalpando",
    "Israel Muñoz Velasco",
    "Israel Ramos García",
    "Isvi René Aguilar Sánchez",
    "Itzel Aidé Vargas Pérez",
    "Itzel Becerra Absalón",
    "Itzel Enríquez Aguirre",
    "Itzel Guzmán Vázquez",
    "Itzel Marisol Garnica Palafox",
    "Itzel Sigala Regalado",
    "Itzel Susana de la Rosa Lara",
    "Itzhel García Torres",
    "Itzia Eréndira Nieto López",
    "Ivette Ruiz Boijseauneau",
    "Ivonne Judith Hernández Hernández",
    "Iván Adrián Oropeza Pérez",
    "Iván Axell Gómez Ramos",
    "Iván Ramiro Espínola Alvarado",
    "J. Guadalupe Bañuelos Muñetón",
    "Jacqueline Quintana Hinojosa",
    "Jaime Alejandro García Villeda",
    "Jaime Ayala Pérez",
    "Jaime Castillo Torres",
    "Jaime Castro Pérez",
    "Jaime Daniel García Argueta",
    "Jaime Eugenio Antonio Pallares",
    "Jaime Fabian Vázquez De la Rosa",
    "Jaime Vázquez Alamilla",
    "Jaime Zamora Chimal",
    "Jairo Israel Valdez Olmos",
    "James Enrique González Flores",
    "Janikua Floritta Nelson Mora",
    "Jaqueline Rafaela Dolores Cañetas Ortega",
    "Javier Axosco Marin",
    "Javier Eduardo Rodríguez Gónzalez",
    "Javier León Cotonieto",
    "Javier Mas Ruiz",
    "Javier Páez Cárdenas",
    "Javier Roberto Rubalcava Cortés",
    "Javier Valdez Quijada",
    "Javier de Jesús Cortés Aguirre",
    "Jazmín Carranza Gallardo",
    "Jazmín Deneb Ortigosa Gutiérrez",
    "Jazmín de Jesús Santillán Manjarrez",
    "Jeanett Monroy Anzueto",
    "Jehú López Aparicio",
    "Jennyfer Guadalupe Moreno Moreno",
    "Jerónimo Alonso Cortez Quezada",
    "Jesica Espino González",
    "Jessica Angélica Jaurez Rosas",
    "Jessica Paola Sánchez Toro",
    "Jessica Raquel Hernández Pérez",
    "Jessica Santizo Galicia",
    "Jessica Sarahi Méndez Rincón",
    "Jesus Adrian Celis González",
    "Jesus Lizardo Cruz Romo",
    "Jesús Alberto Díaz Cruz",
    "Jesús Alberto León Flores",
    "Jesús Alberto Peralta Celerino",
    "Jesús Alberto del Olmo Márquez",
    "Jesús Alquicira Mireles",
    "Jesús Alvarado Ortega",
    "Jesús Cruz Rojas",
    "Jesús David Carrillo Santamaría",
    "Jesús Delgado Aguillón",
    "Jesús Emmanuel Ortega Guzmán",
    "Jesús Garduño Mejía",
    "Jesús Iván Saavedra Martínez",
    "Jesús Manuel Mayorquín García",
    "Jesús Paz Méndez",
    "Jesús Ramírez Morales",
    "Jesús Ramírez Santos",
    "Jesús Villagómez Chávez",
    "Jesús Ángel Arenas Alatorre",
    "Jesús Ángel Núñez Zimbrón",
    "Jhonatan Camilo Rodríguez Porras",
    "Jhonnayker David Paredes Márquez",
    "Jimena Ugalde Flores",
    "Jimmy Hernández Morales",
    "Joel Espinosa Longi",
    "Joel García León",
    "Joel Hernández Hernández",
    "Joel Rubalcava González",
    "Johana Cristal López Hernández",
    "Johnattan Hernández Cumplido",
    "Jonathan Cancino Manríquez",
    "Jonathan Giovanni Gil Juárez",
    "Jonathan López Ruiz",
    "Jonathan Pérez Juárez",
    "Jonathan Ramírez Ramírez",
    "Jonathan Siu Loong Robles Hernández",
    "Jonathan Víctor Jesús Hernández Torres",
    "Jorge Alberto Coleote Domínguez",
    "Jorge Alberto Escutia Sánchez",
    "Jorge Alberto Manero Orozco",
    "Jorge Alfonso García Macedo",
    "Jorge Alonso Santos Mellado",
    "Jorge Amin Seman Harutinian",
    "Jorge Andrés Rosas Ávila",
    "Jorge Antonio Cruz Chapital",
    "Jorge Antonio García Alvarez",
    "Jorge Antonio Montemayor Aldrete",
    "Jorge Arturo Martínez Villegas",
    "Jorge Barragán Argüero",
    "Jorge Damián López Caballero",
    "Jorge David López Maldonado",
    "Jorge Eduardo Rickards Campbell",
    "Jorge Emiliano Alvarez Gil Leyva",
    "Jorge Fernando Rojas Gutiérrez",
    "Jorge Fuentes Fernández",
    "Jorge Fujioka Rojas",
    "Jorge Gregorio Lozano Orozco",
    "Jorge Gustavo Hirsch Ganievich",
    "Jorge Humberto Arce Rincón",
    "Jorge Humberto Del Castillo Spíndola",
    "Jorge Iván Castillo Arellano",
    "Jorge Iván Reyes Hernández",
    "Jorge Karolt Barrera Ballesteros",
    "Jorge Luis Reyes García",
    "Jorge Luis Tamaya Domínguez",
    "Jorge Marcos Martínez Montejano",
    "Jorge Moreno Montes",
    "Jorge Pilo González",
    "Jorge Pérez López",
    "Jorge Ramón Soto Mercado",
    "Jorge Roberto Blanco Martínez",
    "Jorge Urrutia Galicia",
    "Jorge Valle Peña",
    "Jorge de Jesús Ramírez Pimentel",
    "Jose Guillermo Guerrero Mojica",
    "Josefina Herrera Santoyo",
    "Josefina Janeth Miranda Blancas",
    "Josep Anton Moreno Bedmar",
    "Joseph Howard Carmona Hernández",
    "Joshafat Mostalac Valdivieso",
    "Joshua Anthuan Bautista González",
    "Joshua Juárez Cruz",
    "Jossette Calderón Cruz",
    "Josué Cantera Fernández",
    "Josué Esau Romero Ibarra",
    "Josué Manik Nava Sedeño",
    "Josué Orlando Ramírez Jarquín",
    "Josué Trinidad Juárez",
    "José Adrián Gallardo Quiróz",
    "José Agustín Pérez Ahumada",
    "José Alberto Campillo Balderas",
    "José Alberto Martín Ruiz",
    "José Alberto Santiago De la Cruz",
    "José Alejandro Butanda Mejía",
    "José Alejandro Jiménez Acosta",
    "José Alfredo Cobián Campos",
    "José Alfredo Herrera González",
    "José Alfredo Morales Pérez",
    "José Amauri Serrano Lázaro",
    "José Angel Arévalo Avalos",
    "José Antonio De Diego Onsurbe",
    "José Antonio Morales Álvarez",
    "José Antonio Perusquía Cortés",
    "José Antonio Reyes León",
    "José Antonio Valencia Trujillo",
    "José Antonio Vilchis Salazar",
    "José Aquiles Bernal Moreno",
    "José Arnulfo Herrera Lara",
    "José Carlos Gónzalez Vázquez",
    "José Carlos Sánchez Ferrer",
    "José Cruz García Zagal",
    "José Eduardo Chairez Veloz",
    "José Eduardo González Mireles",
    "José Eduardo Gómez Sánchez",
    "José Eduardo Méndez Delgado",
    "José Eduardo Rodríguez Bustamante",
    "José Elías Camarillo Sánchez",
    "José Enrique Pérez Salvador",
    "José Erik Cruz Valderrama",
    "José Ervin Silva González",
    "José Federico Hernández Sánchez",
    "José Fernando Soriano Flores",
    "José Fidel Urquiza Yllescas",
    "José Francisco Malagón García",
    "José Francisco Pérez Barragán",
    "José Gabriel Miramontes Téllez",
    "José Gabriel Ocampo Márquez",
    "José Gerardo López Bonifacio",
    "José Gilberto Amaro Aceves",
    "José Guadalupe Palacios Vargas",
    "José Guadalupe Vázquez Vázquez",
    "José Humberto Arcos Velasco",
    "José Ignacio Cabrera Martínez",
    "José Ignacio Jiménez Mier y Terán",
    "José Iván Patraca Fierro",
    "José Javier Martínez Luengas",
    "José Jesús Carlos Quintanar Sierra",
    "José Juan López Badillo",
    "José Julio Emilio Herrera Velázquez",
    "José Julián Pavón Español",
    "José Lino Samaniego Mendoza",
    "José Luis Arreola Ramírez",
    "José Luis Boisson Ortíz",
    "José Luis Bortolini Rosales",
    "José Luis Gutiérrez Sánchez",
    "José Luis Jiménez  Andrade",
    "José Luis Lugo Castillo",
    "José Luis López Escorcia",
    "José Luis Martínez Trujillo",
    "José Luis Pérez Mazariego",
    "José Luis Ramírez Monsibais",
    "José Luis Rodríguez López",
    "José Luis Rosas Huerta",
    "José Luis Salinas Gutiérrez",
    "José Luis Torres Rodríguez",
    "José Luis del Río Valdés",
    "José Luis Álvarez García",
    "José Manuel Alvarado Reyes",
    "José Manuel Luna Ramos",
    "José Martín Mijangos Tovar",
    "José María Villagómez Quintos",
    "José Miguel Cervantes Cervantes",
    "José Norberto Espíritu Contreras",
    "José Oscar Rosales Vergara",
    "José Perea Ocampo",
    "José Ramón Hernández Balanzar",
    "José Ricardo Rizo Tello",
    "José Roberto Alonso Garduza",
    "José Roberto Ovando Figueroa",
    "José Roberto Torres Bello",
    "José Roberto de la Vega Martínez",
    "José Román Latournerié Cervera",
    "José Rufino Díaz Uribe",
    "José Ríos Montes",
    "José Salvador Zamora Muñoz",
    "José Samuel Rodríguez Olguín",
    "José Santos",
    "José Teodoro Hernández Treviño",
    "José de Jesús Galaviz Casas",
    "José de Jesús Ojeda González",
    "José Ángel Frías García",
    "Juan Adrián Reyes Cervantes",
    "Juan Alberto Guzmán García",
    "Juan Andrés Orozco Gutiérrez",
    "Juan Arturo Briones González",
    "Juan Canek Ortega Sánchez",
    "Juan Carlos Alonso Huitrón",
    "Juan Carlos Badillo Martínez",
    "Juan Carlos Balleza García",
    "Juan Carlos Campuzano Caballero",
    "Juan Carlos Cheang Wong",
    "Juan Carlos D'Olivo Saez",
    "Juan Carlos Del Valle Rosales",
    "Juan Carlos Fernández Morelos",
    "Juan Carlos Flores Vázquez",
    "Juan Carlos Gallardo Pérez",
    "Juan Carlos García Altamirano",
    "Juan Carlos Gomora García",
    "Juan Carlos Guapilla Salamanca",
    "Juan Carlos Gómez Verjan",
    "Juan Carlos Peña Becerril",
    "Juan Carlos Sánchez Balanzar",
    "Juan Carlos Vargas Aguilar",
    "Juan Diego Amaya Figueroa",
    "Juan Diego Terán Páez",
    "Juan Enrique Fornoni Agnelli",
    "Juan Flores Torres",
    "Juan Gabriel Herrera Alva",
    "Juan José Alba González",
    "Juan José Leal García",
    "Juan José Montellano Ballesteros",
    "Juan Luis Chávez Pacheco",
    "Juan López Patiño",
    "Juan Manuel Estrada Rivera",
    "Juan Manuel Germán Acacio",
    "Juan Manuel González López",
    "Juan Manuel Martínez Nuño",
    "Juan Manuel Rodríguez Caso",
    "Juan Manuel de la Huerta Jiménez",
    "Juan Morales Rodríguez",
    "Juan Orendain Almada",
    "Juan Pablo León Gómez",
    "Juan Pablo Rodríguez Villagrán",
    "Juan Pablo Sánchez Soriano",
    "Juan Ramón Rodríguez Córdova",
    "Juan Ramón Sánchez Jácome",
    "Juan Rangel González",
    "Juan Rubén Gómez Solano",
    "Juana Patricia Méndez Pérez",
    "Judith Campos Cordero",
    "Judith Magdalena Vera López",
    "Julia Anai Ojeda Alonso",
    "Julieta Jujnovsky Orlandini",
    "Julio Alfonso Pérez Flores",
    "Julio Cesar Ramírez Martínez",
    "Julio César Cedillo Sánchez",
    "Julio César Cruz Cárdenas",
    "Julio César García Zebadúa",
    "Julio César Guevara Bravo",
    "Julio César Marentes Mosqueda",
    "Julio César Misael Monroy González",
    "Julio César Pardo Dañino",
    "Julio César Pérez Jiménez",
    "Julio Eduardo Roque Morán Andrade",
    "Julio Javier Martinell Benito",
    "Julio Martín Espinosa Casares",
    "Julio Robles Flores",
    "Julián Alexander Mendivil Nieto",
    "Karen Escutia Solís",
    "Karen Lanzguerrero Obeid",
    "Karen Lucero Roldán Serrato",
    "Karen Mariana Luján Hérnandez",
    "Karen Patricia Volke Sepúlveda",
    "Karen Susana Villa Aguirre",
    "Karen Suárez Larios",
    "Karen Valencia García",
    "Karime Alejandra Pérez Campos",
    "Karina Elizabeth de Jesús González",
    "Karina García Buendía",
    "Karina Hernández Flores",
    "Karina Portillo Cortez",
    "Karina Robles Martínez",
    "Karina Vargas Cruz",
    "Karla Adriana Esquivel Guzmán",
    "Karla Berenice Acosta Virgen",
    "Karla Edith Arizmendi García",
    "Karla Elisa Juárez Contreras",
    "Karla Eva Abreo Leon",
    "Karla Fabiola Meza Sosa",
    "Karla Flores Celis",
    "Karla Genoveva Bassols Bello",
    "Karla Giovana García Hernández",
    "Karla Ivonne de la Cruz de la Cruz",
    "Karla Lizardi Solís",
    "Karla Pamela Reveles Martínez",
    "Karla Paola García Pelagio",
    "Karla Ramírez Pulido",
    "Karla Ruíz de la Luz",
    "Karla Yadira Olalde Estrada",
    "Karyme Ivette Azpeitia García",
    "Kassandra Salguero Martínez",
    "Kathleen Ann Babb Stanley",
    "Katia Aimeé Olea y Wagner",
    "Katia Michelle Villarnobo Gonzalez",
    "Katya Dafne Guadarrama Orozco",
    "Kenia Lolbeg Juayerk Herrera",
    "Kenia Paola Márquez Santamaria",
    "Kenya Verónica Espinosa Hurtado",
    "Kernel Enrique Prieto Moreno",
    "Kinrha Aguirre de la Luz",
    "Laura Adriana Izquierdo San Agustín",
    "Laura Enedina Soto Serna",
    "Laura Helena González Trueba",
    "Laura Ivonne Martín Pérez",
    "Laura Jocelyn Rosales Ponce de León",
    "Laura Kawasaki Watanabe",
    "Laura Olivia Villegas Olvera",
    "Laura Ortiz Bobadilla",
    "Laura del Carmen Vargas Parada",
    "Leah Daniela Muñoz Contreras",
    "Leda Carolina Torres Maldonado",
    "Leobardo Fernández Román",
    "Leobardo Terpán Acuña",
    "Leonardo Alejandro Beltrán Rodríguez",
    "Leonardo Faustinos Morales",
    "Leonardo González Quiroz",
    "Leonardo Iván Zapata Fonseca",
    "Leonardo Javier García Ayala",
    "Leonardo Javier Sánchez Peniche",
    "Leonardo Osvaldo Alvarado Cárdenas",
    "Leonardo Tinajero Andrade",
    "Leonardo Tomás Martínez Trueba",
    "Leonardo Uhthoff Rodríguez",
    "Leonel Rito Rodríguez",
    "Leonid Serkin",
    "Leslie Paola Sánchez Victoria",
    "Leslie Yoselin Aguilar Ruíz",
    "Lesly Corina Castañeda Carlos",
    "Leticia Guadalupe Cienfuegos Blancas",
    "Leticia Margarita Ochoa Ochoa",
    "Lev Orlando Jardón Barbolla",
    "Levia Sefira Mendieta Noguez",
    "León Felipe Villalobos Sánchez",
    "Libertad Rosalia Castro Colina",
    "Liborio Morán Zanabria",
    "Lidia Escutia Guadarrama",
    "Lilian Gabriela Valencia Turcotte",
    "Liliana Gaytán Cruz",
    "Liliana Itze López Olmedo",
    "Liliana Peralta Hernández",
    "Liliana Sánchez Estrada",
    "Linda Mariana Martínez Ramos",
    "Lisette Chávez García",
    "Lizbeth Naranjo Albarrán",
    "Lizbeth Rossana Ayala Domínguez",
    "Lizeth Mariel Zavala Ocampo",
    "Lizeth Sánchez Zamora",
    "Loiret Alejandría Dosal Trujillo",
    "Lorena Arias Montaño",
    "Lorena Morales Callejas",
    "Lorena del Carmen Jiménez Naranjo",
    "Lorenzo Antonio Alvarado Cabrera",
    "Lourdes Gabriela Soid Raggi",
    "Lourdes Martín Aguilar",
    "Lourdes Teresa Agredano Moreno",
    "Lucero Cetina Arenas",
    "Lucía Medina Gómez",
    "Lucía Yoscelina Centeno Betanzos",
    "Luis Abel Castorena Martínez",
    "Luis Abraham García Hernández",
    "Luis Adrián Campos Ávila",
    "Luis Adrián Pedroza Rojas",
    "Luis Alberto Dacomba Méndez",
    "Luis Alberto Galván Contreras",
    "Luis Alberto Hernández Pérez",
    "Luis Alberto Jiménez Ramírez",
    "Luis Alberto Ramírez Bermudez",
    "Luis Alberto Vázquez Maisón",
    "Luis Angel Araiza Bautista",
    "Luis Antonio Cedeño Pérez",
    "Luis Antonio García Contreras",
    "Luis Antonio Madrigal Butrón",
    "Luis Antonio Paredes Rivas",
    "Luis Antonio Pérez López",
    "Luis Antonio Rincón Solís",
    "Luis Antonio Sánchez González",
    "Luis Artemio Martínez Vázquez",
    "Luis Daniel Pérez Sámano",
    "Luis Daniel Rodríguez García",
    "Luis Daniel Rojas Mares",
    "Luis David Alcaraz Peraza",
    "Luis David Ginez Vázquez",
    "Luis David Reyes Sáenz",
    "Luis Edgar Flores Ayala",
    "Luis Eduardo García Hernández",
    "Luis Eduardo Ramos Solís",
    "Luis Efraín Moreles Vázquez",
    "Luis Enrique Conrado Alarcón",
    "Luis Enrique Nava García",
    "Luis Enrique Quintanar Cortés",
    "Luis Enrique Reyes Rodríguez",
    "Luis Enrique Serrano Gutiérrez",
    "Luis Enrique Tintor Alonso",
    "Luis Felipe Chan Corona",
    "Luis Felipe Gutierrez Vilchis",
    "Luis Felipe Javier Barros y Villa",
    "Luis Felipe Jiménez García",
    "Luis Fermín Martínez Manzo",
    "Luis Fernando Flores Tiburcio",
    "Luis Fernando Galicia Cruztitla",
    "Luis Fernando García Mora",
    "Luis Fernando Magaña Solís",
    "Luis Fernando Quezada Mata",
    "Luis Fernando Villagomez Lazo de la Vega",
    "Luis Flores Morales",
    "Luis Francisco Bazán Estrada",
    "Luis Gabriel Aguilar Estrada",
    "Luis Gerardo Flores Roldán",
    "Luis Gerardo Hernández Chávez",
    "Luis Gerardo Romero Chora",
    "Luis German Pérez Hernández",
    "Luis Guillermo Constante Pérez",
    "Luis Guillermo García Jácome",
    "Luis Gustavo Maldonado Toral",
    "Luis Gutiérrez Melgarejo",
    "Luis Jesús Turcio Cuevas",
    "Luis Manuel León Rossano",
    "Luis Manuel Reyes de la Luz",
    "Luis Mariscal Becerra",
    "Luis Medrano González",
    "Luis Miguel Burciaga Cifuentes",
    "Luis Miguel Rojas Pérez",
    "Luis Muñoz Flores",
    "Luis Odín Estrada Ramos",
    "Luis Pablo Aldama Molina",
    "Luis Rey Rutiaga Robles",
    "Luis Ricardo López Villafán",
    "Luis Rodríguez Fernández",
    "Luis Vicente Ruiz Hernández",
    "Luis Xavier González Méndez",
    "Luis Zambrano González",
    "Luisa Alejandra Granados Hernández",
    "Luisa Fernanda Higueras Montaño",
    "Luisa Gabriela Del Valle Díaz Muñoz",
    "Lurel Cedeño Peña",
    "Luz Anette Claro Mendoza",
    "Luz Arely Carrillo Olivera",
    "Luz Elena Hernández Maldonado",
    "Luz Estela Zamudio Beltrán",
    "Luz María Sil Berra",
    "Luz Selene Velázquez Bermúdez",
    "Luz Vianney Cortés González",
    "Lydia Ramírez Martínez",
    "Lázaro Guevara López",
    "Lázaro Huerta Arcos",
    "Lía Natsuko Rivera Yoshida",
    "Ma Beatriz Sánchez Monroy",
    "Ma. Susana Barrera Ocampo",
    "Magali Blanca Isabel Honey Escandón",
    "Magali Louise Marie Folch Gabayet",
    "Maira Sarai Montejo Cruz",
    "Malinali Gónzalez Lara",
    "Malinalli Wong Rueda",
    "Manan Vyas",
    "Manuel Alcántara Juárez",
    "Manuel Alejandro Zúñiga Pérez",
    "Manuel Amida Álvarez Gutiérrez",
    "Manuel Campos García",
    "Manuel Cristóbal López Michelone",
    "Manuel Gerardo Quintana García",
    "Manuel Hernández Hernández",
    "Manuel Silva Hernández",
    "Manuel Soto Romero",
    "Manuel Tejada Wriedt",
    "Mara Jazmín Cruz Barrena",
    "Marcela Dolores Grether González",
    "Marcela Regina Beltrán Sánchez",
    "Marcela Ruedas Medina",
    "Marcelo Del Castillo Mussot",
    "Marco Alejandro Corrales Avalos",
    "Marco Alejandro Suárez Atilano",
    "Marco Antonio Ayala Torres",
    "Marco Antonio Diego Geronimo",
    "Marco Antonio García Fernández",
    "Marco Antonio Jiménez Limas",
    "Marco Antonio Jiménez Serrano",
    "Marco Antonio López Ortiz",
    "Marco Antonio Martínez Villalobos",
    "Marco Antonio Merchand Medina",
    "Marco Antonio Montes de Oca Balderas",
    "Marco Antonio Oliveros Hérnandez",
    "Marco Antonio Quintero Santiago",
    "Marco Antonio Sánchez Alejo",
    "Marco Antonio Zaragoza Campillo",
    "Marco Arieli Herrera Valdez",
    "Marco David Ornelas Cruces",
    "Marco Fabio Ortiz Ramírez",
    "Marco Gustavo Serna Estrada",
    "Marco Vladimir Lemus Yáñez",
    "Marcos Alejandro García García",
    "Marcos Ley Koo",
    "Margarita Elvira Chávez Cano",
    "Margarita Espinosa Sevilla",
    "Margarita Eugenia del Socorro Rosado Solís",
    "Margarita Jacaranda Rosendo Pineda",
    "Margarita Ojeda Carrasco",
    "Margarita Rivera Hernández",
    "Margarita Sánchez y Sánchez",
    "Mariana De la Rosa Juárez",
    "Mariana Estefania Aviles Alarcon",
    "Mariana Esther Torres Revuelta",
    "Mariana Garduño Reyes",
    "Mariana Guadalupe Cartajena Alcántara",
    "Mariana Gómez García",
    "Mariana Martínez González",
    "Mariana Morayma Bernal Esquivel",
    "Mariana Palma Tenango",
    "Mariana Susana Hernández Leal",
    "Mariana Vargas Magaña",
    "Mariana Vargas Sánchez",
    "Mariana Zareth Nava López",
    "Mariana del Olmo Ruiz",
    "Mariangely López González",
    "Mariano Chernicoff Minsberg",
    "Maricela Villagrán Santa Cruz",
    "Maricruz Rosas Velázquez",
    "Mario Aarón Gutiérrez Sánchez",
    "Mario Adrián Colín Valero",
    "Mario Alberto Villa Carapia",
    "Mario Arturo Nieto Butron",
    "Mario Delgadillo Torres",
    "Mario Felipe de Jesús González",
    "Mario González Ruiz",
    "Mario Medina Torres",
    "Mario Orozco Morales",
    "Marisa Ramírez Morales",
    "Marisol Amézcua López",
    "Marisol Chávez Estrada",
    "Marisol Flores Castro",
    "Marisol Ocampo Sandoval",
    "Marlen Mondragón Huerta",
    "Marlen Valdés Fuentes",
    "Marlon Uriel de la Cruz Guzmán",
    "Martha Angélica Montes Fonseca",
    "Martha Evelia Cruz Rodríguez",
    "Martha Gabriela Gaxiola Cortés",
    "Martha González Gutiérrez",
    "Martha Rosete Aguilar",
    "Martín Alarcón Ronzón",
    "Martín Alberto Herrera Garza",
    "Martín Alejandro Fuentes Cano",
    "Martín Gutiérrez Santillán",
    "Martín Martínez Estrada",
    "Martín Romero Martínez",
    "Marysol Trujano Ortega",
    "María Alexandra Rodríguez Sastre",
    "María Alicia Villela González",
    "María Ana del Carmen Fernández Álamo",
    "María Angélica Cervantes Alcayde",
    "María Berenice Mendoza Gamez",
    "María Berenit Mendoza Garfias",
    "María Catalina Espinoza Hernández",
    "María Cristina Gutiérrez Delgado",
    "María Cristina Julia Pérez Reyes",
    "María Cristina Velasquillo Martínez",
    "María Dolores Maravilla Meza",
    "María Edith Ponce Márquez",
    "María Elena Calderón Segura",
    "María Elena García Granados",
    "María Elena Martínez Pérez",
    "María Esther Sánchez Coronado",
    "María Eugenia Muñiz Díaz de León",
    "María Fernanda Barrios Vega",
    "María Fernanda Clever Uribe",
    "María Fernanda Gil Leyva Villa",
    "María Fernanda Mendoza Castillo",
    "María Fernanda Ramírez Ayala",
    "María Gloria Castilleja Leyva",
    "María Guadalupe Barajas Guzmán",
    "María Guadalupe Bribiescas Chávez",
    "María Guadalupe Camacho Sánchez",
    "María Guadalupe Guzmán Bárcenas",
    "María Guadalupe Ordaz Téllez",
    "María Guadalupe Ponce Vélez",
    "María Isabel Briseño Sánchez",
    "María Isabel De la Cruz Laina",
    "María Isabel Rodríguez Romero",
    "María Ivonne Reyes Ortega",
    "María Izabel Morales Amador",
    "María Jaritzi Camacho Serrano",
    "María Laura González Resendiz",
    "María Luisa Durán Pastén",
    "María Luisa Escobar Sánchez",
    "María Luisa Marquina Fábrega",
    "María Magdalena Contreras Pacheco",
    "María Magdalena González Sánchez",
    "María Magdalena López Ramírez",
    "María Nayeli Ortega Villegas",
    "María Sol Robledo y Monterrubio",
    "María Teresa Rubio Monroy",
    "María Victoria Guzmán Sánchez",
    "María Ximena Lezama Hernández",
    "María de Jesús Guadalupe Vázquez Cuevas",
    "María de Jesús Hernández León",
    "María de Lourdes Barbosa Saldaña",
    "María de Lourdes Segura Valdez",
    "María de Lourdes Serrano Sánchez",
    "María de Lourdes Tavera Sierra",
    "María de Luz Gasca Soto",
    "María de la Asunción Preisser Rodríguez",
    "María de la Luz Espinosa Fuentes",
    "María de la Luz Jimena de Teresa de Oteyza",
    "María de los Dolores Sánchez Castañeda",
    "María de los Ángeles Cancino Rodezno",
    "María de los Ángeles Garduño Crespo",
    "María de los Ángeles Sandoval Romero",
    "María del Carmen Fernández García",
    "María del Carmen Guzmán Cornejo",
    "María del Carmen Hernández Alvarez",
    "María del Carmen Hernández Ayuso",
    "María del Carmen Miñana Solís",
    "María del Carmen Uribe Aranzábal",
    "María del Jazmín Aguilar Medina",
    "María del Pilar Piñones Contreras",
    "María del Pilar Segarra Alberú",
    "María del Pilar Valencia Saravia",
    "María del Rocío López Vargas",
    "María del Rocío Sánchez López",
    "María del Rosario Espinosa Tufiño",
    "Maureen Galindo Cabrera",
    "Mauricio Aguilar González",
    "Mauricio Gabriel Arredondo Fernández Cano",
    "Mauricio García Vergara",
    "Mauro Emiliano Chávez Zamora",
    "Max Alcántara Castellanos",
    "Max Neumann Coto",
    "Maximiliano Rojas Zaputovich",
    "Maximino Avendaño Alejo",
    "Maya Lol Sosa Salas",
    "Mayo Villagrán Muniz",
    "Mayra Dinorah Álvarez Santos",
    "Mayra Flores Tolentino",
    "Mayra Guadalupe Canseco Rivas",
    "Mayra Vianey Gómez Naranjo",
    "Melisa Meztli Méndez Méndez",
    "Melissa Ponce Sosa",
    "Micaela Julia Raga",
    "Miguel Adán Jáurez Martínez",
    "Miguel Alcubierre Moya",
    "Miguel Alejandro Maldonado Gordillo",
    "Miguel Angel Almanza Melgoza",
    "Miguel Angel Guadarrama García",
    "Miguel Angel Méndez Alarcón",
    "Miguel Angel Palomino Garibay",
    "Miguel Angel Préstegui González",
    "Miguel Angel Pérez León",
    "Miguel Angel Sánchez Alcántara",
    "Miguel Angel Torres Martínez",
    "Miguel Angel Veloz Lucas",
    "Miguel Arturo Ballesteros Montero",
    "Miguel Betanzo Partida",
    "Miguel Carrillo Barajas",
    "Miguel Enrique Patiño Salazar",
    "Miguel Ignacio Romero Cortés",
    "Miguel Manterola Obregón",
    "Miguel Mireles Padilla",
    "Miguel Murguía Romero",
    "Miguel Pérez Flores",
    "Miguel Ángel Campos González",
    "Miguel Ángel Carrillo Lucía",
    "Miguel Ángel Chong Rodríguez",
    "Miguel Ángel Corona García",
    "Miguel Ángel Galeana Morán",
    "Miguel Ángel García Cruz",
    "Miguel Ángel Pérez Pastenes",
    "Miguel Ángel Quetzeri Santiago",
    "Miguel Ángel Rosas Paz",
    "Miguel Ángel Solís Atala",
    "Miguel Ángel Zúñiga Pérez",
    "Mijail Castillo Yescas",
    "Mindy Yaneli Huerta Pérez",
    "Minerva Ortíz Pérez",
    "Miriam Beatriz Rodríguez González",
    "Miriam Erandi Reyna Fabián",
    "Miriam Fernanda Hérnandez Álvarez",
    "Miriam Flores Rojas",
    "Miriam Marisol Tellez Cruz",
    "Miriam Sosa Díaz",
    "Mirian Leon Faro",
    "Mirna Villavicencio Torres",
    "Miryam Nava Catorce",
    "Mirza Patricia Ortega Olivares",
    "Misael Salvador Pedraza",
    "Moises Olaf Rosas Tavera",
    "Moises Zeleny Mora",
    "Moisés Antonio Rosas Olivares",
    "Moisés Isaac Espinosa Espinosa",
    "Monserrat Bizarro Sordo",
    "Monserrat Martín Sánchez Herrera",
    "Monserrat Moysén Carbajal",
    "Monserrat Negrete Derramadero",
    "Montserrat Arias Basilio",
    "Mucuy-Kak del Carmen Guevara Aguirre",
    "Mónica Araceli Canales Lizaola",
    "Mónica Elías González",
    "Mónica Eugenia Zenil Medellín",
    "Mónica Iliana Sánchez Zaragoza",
    "Mónica Miranda Mijangos",
    "Mónica Ramírez Vázquez",
    "Mónica Salmerón Estrada",
    "Nadia Alejandra Rivero Segura",
    "Nalleli Elvira Lara Díaz",
    "Nallely Vázquez Salvador",
    "Nancy Contreras Moreno",
    "Nancy Galvez Reyes",
    "Nancy Guadalupe Arizpe Ramos",
    "Nancy Martínez Correa",
    "Nancy Ortiz Mendoza",
    "Nancy Pérez Cano",
    "Naomi Itzel Reyes Granados",
    "Nara Sharline Alvarado Cervantes",
    "Narda Cordero Michel",
    "Natalia Bárbara Mantilla Beniers",
    "Natalia Jonard Pérez",
    "Natalia Zavala Velázquez",
    "Natalie Elizabeth Sánchez López",
    "Nataly Bolaño Martínez",
    "Nataly Quiroz González",
    "Nathalie Marie Gómez Walton",
    "Nathalie Roberte Chantal Cabirol",
    "Nayeli Torres Ramírez",
    "Neil Charles Bruce Davidson",
    "Nelly Michelle Solano Pinelo",
    "Nelson Arturo Izazaga Jijón",
    "Nicole Lissette González Vázquez",
    "Nicte Andrea Gutiérrez Puente",
    "Nidia Elizabeth Gómez Ortega",
    "Nilse Pamela Romero Basurto",
    "Nitzerindany Alejandra López Pérez",
    "Nivia Rocio Antonio Rubio",
    "Noel Jaramillo Arce",
    "Nora Elizabeth Galindo Miranda",
    "Nora Gavira Durón",
    "Norberto Javier Rivas González",
    "Norma Yanet Sánchez Torres",
    "Noé Becerra Lobato",
    "Noé Bárcenas Torres",
    "Noé Francisco Ponce Campos",
    "Noé Pacheco Coronel",
    "Noé Salomón Hernández Sánchez",
    "Néstor Enrique Ortiz Madrigal",
    "Néstor Fabián Díaz Martínez",
    "Octavio Abraham Bureos Lecona",
    "Octavio Baltasar Zapata Fonseca",
    "Octavio Eduardo Vizcaya Xilotl",
    "Octavio González Caballero",
    "Octavio Manero Brito",
    "Octavio Quintanar Retama",
    "Odín Miguel Escorza Soria",
    "Ofelia Cepeda Camargo",
    "Olga Olinca Galván de la Cruz",
    "Oliver Ariel López Conde",
    "Oliver Huerta Carranza",
    "Oliver Xavier López Corona",
    "Olivia Amanda García Garduño",
    "Olivia Yáñez Ordóñez",
    "Omahr Garciapiña Arteaga",
    "Omar Alejandro Pompa García",
    "Omar Emiliano Aparicio Trejo",
    "Omar Guillermo Morales Saavedra",
    "Omar Hernández Ordóñez",
    "Omar Lagunas Calvo",
    "Omar Patricio Juárez Álvarez",
    "Omar Páez Gómez",
    "Omar Rafael Alemán Muñoz",
    "Omar Rodríguez Torres",
    "Omar Vigueras Herrera",
    "Omar de la Riva Torres",
    "Omar Ávalos Hernández",
    "Orlando René Martínez Medrano",
    "Oscar Adrián Ramírez Kantun",
    "Oscar Alan Cordero Vilchis",
    "Oscar Alberto Flores Villela",
    "Oscar Alfredo Palmas Velasco",
    "Oscar Aranda Martínez",
    "Oscar Aristidez Martinez Salas",
    "Oscar Chávez Molina",
    "Oscar Eduardo Hernández Cervantes",
    "Oscar Eduardo Mani Cano",
    "Oscar Eduardo Morales Toledo",
    "Oscar Everardo Flores Choperena",
    "Oscar Genaro de Lucio Morales",
    "Oscar Guadalupe Millán Tamayo",
    "Oscar Gustavo Morales Olivares",
    "Oscar Hernández Constantino",
    "Oscar Javier Parada Parra",
    "Oscar Tadeo Leal Villegas",
    "Ossiel Aguilar Espíndola",
    "Osvaldo Alfonso Téllez Nieto",
    "Osvaldo Ponce Hernández",
    "Osvaldo Uriel Calderón Dorantes",
    "Othón Alcántara Ayala",
    "Pablo Alberto Álvarez Pérez",
    "Pablo García Martínez",
    "Pablo Girzikovsky Paredes",
    "Pablo Josué Peña Molina",
    "Pablo Rosell González",
    "Pablo de la Mora y Palomar Askinasy",
    "Pactli Fernando Ortega González",
    "Paloma Hernández Zapata",
    "Paloma Zubieta Lopez",
    "Paola Ballesteros Zebadúa",
    "Paola Berenice Guzmán Rodríguez",
    "Paris Olalde Estrada",
    "Pascual Di Bella Nava",
    "Patricia Astrid González Ávila",
    "Patricia Cano Sánchez",
    "Patricia Goldstein Menache",
    "Patricia Guevara Fefer",
    "Patricia Magaña Rueda",
    "Patricia Pellicer Covarrubias",
    "Patricia Raquel Avilés Mandujano",
    "Patricio Ricardo Garcia Vázquez",
    "Patricio Vázquez Fernández",
    "Paula Mercedes Martes Camargo",
    "Paula Zepeda Gutiérrez",
    "Paulo Rodrigo Romo de Vivar Martínez",
    "Pavel David Sulca Cavero",
    "Pedro Alejandro de Jesús Magaña Melgoza",
    "Pedro Antonio Quinto Su",
    "Pedro Cebrian Xochihuila",
    "Pedro Eduardo Miramontes Vidal",
    "Pedro García Barrera",
    "Pedro Humberto Santa Rita Alcibia",
    "Pedro Ismael Guerrero Enciso",
    "Pedro Luis Soto Tejeda",
    "Pedro Martín Hernández Quiroz",
    "Pedro Porras Flores",
    "Pedro Rivera Herrera",
    "Pedro Ulises Cervantes González",
    "Pedro Xavier Contla Romero",
    "Penélope Rodríguez Zamora",
    "Perla Eugenia Ugalde Muñiz",
    "Perla Patricia Hernández Colorado",
    "Petra Rubí Pantaleón Mondragón",
    "Pierre Michel Bayard",
    "Pilar Gabriela Ibáñez Hernández",
    "Pilar Raquel Ovalle Marroquin",
    "Ponciano García Gutiérrez",
    "Quentin Edouard Gendron",
    "Radamés Ricardo Reynoso Manríquez",
    "Rafael Antolín Jiménez",
    "Rafael Lugo Huitrón",
    "Rafael López Martínez",
    "Rafael Magaña López",
    "Rafael Mendoza García",
    "Rafael Miranda Cordero",
    "Rafael Nieto Camacho",
    "Rafael Padilla Ramírez",
    "Rafael Reyes Sánchez",
    "Rafael Rodríguez Martínez",
    "Rafael Villanueva Olea",
    "Rafael de Villa Magallón",
    "Rafael Ángel Barrio Paredes",
    "Ramiro Cruz Durán",
    "Ramsés Humberto Mena Chávez",
    "Ramón Arcos Morales",
    "Ramón Gustavo Contreras Mayen",
    "Ramón López Peña",
    "Ramón Reyes Carrión",
    "Ramón Tamayo Andrade",
    "Raybel Andrés García Ancona",
    "Raymundo Díaz Flores",
    "Raymundo Manjarrez Chávez",
    "Raúl Arturo Espejel Morales",
    "Raúl Caudillo Viurquez",
    "Raúl Eduardo Martínez Dámaso",
    "Raúl Isaac López Esquivel",
    "Raúl Jaime Torres Rojas",
    "Raúl Navarro Guevara",
    "Raúl Patricio Esquivel Sirvent",
    "Raúl Rodríguez Barrera",
    "Raúl Rueda Díaz del Campo",
    "Rebeca María López Rivas",
    "Rebeca Rangel Melgoza",
    "Rebeca Sarai Aragón Castro",
    "Regina Ortiz Zamora",
    "Renato Carlos Calleja Castillo",
    "Renato Leriche Vázquez",
    "Renato León Rodríguez",
    "Renela María Valladares Mc Nelis",
    "René Hernández Rivera",
    "René Ledesma Alonso",
    "René de Jesús Cárdenas Vázquez",
    "Reyna Guadalupe Ramírez De la Torre",
    "Reyna Pineda González",
    "Ricardo Alberto Weder Zaninovich",
    "Ricardo Alfonso González Hernández",
    "Ricardo Arencibia Jorge",
    "Ricardo Badillo Macías",
    "Ricardo Castañeda Martínez",
    "Ricardo Clairín Meza",
    "Ricardo Colín Núñez",
    "Ricardo Covarrubias Yeffal",
    "Ricardo César Arzate Trujillo",
    "Ricardo Damián Rodríguez",
    "Ricardo David Quiroz Baez",
    "Ricardo Enrique Castro Torres",
    "Ricardo Enrique Pérez Villanueva",
    "Ricardo García Sandoval",
    "Ricardo González Campuzano",
    "Ricardo Gómez Aíza",
    "Ricardo Hernández Morales",
    "Ricardo López López",
    "Ricardo Mariño Pérez",
    "Ricardo Martín Hernández Flores",
    "Ricardo Morales Jimenez",
    "Ricardo Noguera Solano",
    "Ricardo Ramírez Aldana",
    "Ricardo Strausz Santiago",
    "Ricardo Vasconcelos Ginzo",
    "Ricchy Alain Pérez Chevanier",
    "Rita Esther Zuazua Vega",
    "Rita Fonseca Álvarez",
    "Roberto Antonio Zamora Zamora",
    "Roberto Carrillo Lárraga",
    "Roberto Guillermo Dehesa Borja",
    "Roberto Hinojosa Nava",
    "Roberto Ignacio Márquez Hernández",
    "Roberto Márquez Huitzil",
    "Roberto Méndez Méndez",
    "Roberto Pichardo Mendoza",
    "Roberto Romero Ramírez",
    "Roberto Rosas Espinosa",
    "Roberto Sosa Nava",
    "Roberto Ysacc Sato Berrú",
    "Rocío Aguilar Fernández",
    "Rocío Juárez Cuatlapantzi",
    "Rocío Jáuregui Renaud",
    "Rocío Leonel Gómez",
    "Rocío Salceda Sacanelles",
    "Rocío del Pilar Aguilar Benítez",
    "Rodolfo Austria Cruz",
    "Rodolfo Ezequiel López Romero",
    "Rodolfo Salas Lizana",
    "Rodolfo San Agustín Chi",
    "Rodrigo Alejandro Sánchez Morales",
    "Rodrigo Alfonso Martín Salas",
    "Rodrigo Baruch Rivera Rico",
    "Rodrigo Basaldud Ortega",
    "Rodrigo Daniel Arvizu Hernández",
    "Rodrigo Domínguez López",
    "Rodrigo Fernando Velázquez Cruz",
    "Rodrigo García Formentí Mendieta",
    "Rodrigo Guadalupe Chávez Jiménez",
    "Rodrigo Iván Rodríguez Barrera",
    "Rodrigo Morales Cabrera",
    "Rodrigo Muñoz Avilés",
    "Rodrigo Perusquía Cortés",
    "Rodrigo Rena González",
    "Rodrigo Robles Montero",
    "Rodrigo Serafín Adame Ibarra",
    "Rodrígo Vega Vilchis",
    "Rogelio Aguilar Aguilar",
    "Rogelio Alan Medina Covarrubias",
    "Rogelio Alcantar Arenas",
    "Rogelio Fragoso Ramírez",
    "Rogelio Omar Corona Núñez",
    "Rogelio Rodríguez Flores",
    "Rosa Angélica Velázquez Alor",
    "Rosa Elena Tovar Liceaga",
    "Rosa Isela Jasso Flores",
    "Rosa Luz Tavera Sierra",
    "Rosa María Couvert Rojas",
    "Rosa María Méndez Vargas",
    "Rosa Nuria Galindo Solano",
    "Rosa Victoria Villa Padilla",
    "Rosalba Jasso Vargas",
    "Rosalinda Ortiz Sosa",
    "Rosario Mata López",
    "Rosario Ortiz Hernández",
    "Rosario Paredes Gutiérrez",
    "Rosario Pintor Elizalde",
    "Rosendo David Ferrer Figueroa",
    "Rosina Sánchez Thomas",
    "Roxana Acosta Gutiérrez",
    "Roxana Jiménez Jiménez",
    "Roxana Marisol Calderón Olvera",
    "Roxana Mitzayé del Castillo Vázquez",
    "Roxana Wendoline Ruiz Aguilar",
    "Ruben Yvan Maarten Fossion",
    "Rubi Evangelista Casimiro",
    "Rubi Tonantzin Gutiérrez Villanueva",
    "Ruby Lizbeth Almazán Calzada",
    "Rubén Alfaro Quiza",
    "Rubén Andrés Baca González",
    "Rubén Cruz Vázquez",
    "Rubén San Miguel Chávez",
    "Rubén Santamaría Ortiz",
    "Rubí Bustamante García",
    "Ruth Cecilia Vanegas Pérez",
    "Ruth Selene Fuentes García",
    "Saddan Morales Saldaña",
    "Sahara Irlanda García Alegre",
    "Sajid Daniel García Franco",
    "Salvador Elías Venegas Andraca",
    "Salvador López Mendoza",
    "Salvador López Valdés",
    "Salvador Víctor Godoy Salas",
    "Salvador Zaragoza Juárez",
    "Samanta Pérez Arévalo",
    "Sammy Israel Gutiérrez Terrazas",
    "Samuel Martínez Bello",
    "Sandra Antonio Bueno",
    "Sandra Castro Santiuste",
    "Sandra Cristina Ramos García",
    "Sandra Hérnandez Ramos",
    "Sandra Julieta Gutiérrez Ojeda",
    "Sandra Marisol Ramírez Barrera",
    "Sandra Monserrat Bautista Pérez",
    "Sandra Nieves Uribe",
    "Santiago Burgos Puentes",
    "Santiago Fernández Romano",
    "Santiago Lara Jiménez",
    "Santiago López de Medrano Sánchez",
    "Sara Abeijón Malvaez",
    "Sara Alicia Quiroz Barroso",
    "Sara Angélica Ramírez Cañas",
    "Sara Frías Vázquez",
    "Sara Mercedes Fraija Castellanos",
    "Sara Rosario Cruz Morales",
    "Sarahi Hurtado Cortés",
    "Sarahi Ramos Martínez",
    "Sarahí Rosas González",
    "Saraí Montes Recinas",
    "Sarira Sahu",
    "Saul Cruz Espinosa",
    "Saul Ezequiel Rivera De La Luz",
    "Saúl Aguilar Salazar",
    "Saúl Arce Rocha",
    "Saúl Jiménez Yllescas",
    "Saúl López Alcaide",
    "Saúl Noé Ramos Sánchez",
    "Sebastian Rosas Ayala",
    "Sebastián Octavio Rodríguez López",
    "Sebastián Pérez Patricio",
    "Sebastián Solano Juárez",
    "Sebastián Urbina Romo",
    "Selene Marisol Martínez Ramírez",
    "Selene Rubi Islas Sánchez",
    "Semiramis Stephania García Trejo",
    "Sergei Giovanni Quintero Villeda",
    "Sergey Antonyan",
    "Sergio Aburto Castañeda",
    "Sergio Antonio Alcalá Corona",
    "Sergio Arturo Cordero Reyes",
    "Sergio Enrique Solís Nájera",
    "Sergio Enríquez Flores",
    "Sergio Giovanni Bisogno Léon y Vélez",
    "Sergio González Mora",
    "Sergio Hernández López",
    "Sergio Hernández Zapata",
    "Sergio Iker Martínez Juárez",
    "Sergio Iván López Ortega",
    "Sergio López Olivares",
    "Sergio Macías Álvarez",
    "Sergio Martín Martínez Pérez",
    "Sergio Rafael Silvestre Cevallos Ferriz",
    "Sergio Rodolfo Cruz Gómez",
    "Shaira Rocío Hernández Flores",
    "Shunashi Guadalupe Castillo López",
    "Sigfrido Sierra Galván",
    "Silvana Palacios Álvarez",
    "Silvia Bautista Hernández",
    "Silvia Castillo Argüero",
    "Silvia Guzmán Beltrán",
    "Silvia Ivonne San Miguel Rodríguez",
    "Silvia Leticia Malpica Flores",
    "Silvia Patricia Romero Hidalgo",
    "Silvia Raquel Lira Ibarra",
    "Silvia Viridiana Maldonado Zamora",
    "Silvia Yoselín Hernández Basurto",
    "Sofía Grecia López Oropeza",
    "Sofía Guzmán León",
    "Sofía Villers Gómez",
    "Sofía de Jesús Rodas Velasco",
    "Sol Cristians Niizawa",
    "Soledad Ruiz Matus",
    "Sonia María Juárez Orozco",
    "Sonia Nava Salazar",
    "Sonia Vázquez Santana",
    "Stephanie Dondé Rodríguez",
    "Stephanie Pacheco Ordaz",
    "Stephanye Mata González",
    "Suri Karina Martínez Yee",
    "Susana Alejandra Barrera Ávalos",
    "Susana Biro Mc Nichol",
    "Susana Méndez Vázquez",
    "Talia Cipactli Rosas Cabrera",
    "Tamara Donají Valencia López",
    "Tania Azucena Chicalote Jiménez",
    "Tania Eréndira Rivera Torres",
    "Tania Naomi Barajas Pulido",
    "Tanya Marcela González Martínez",
    "Tatiana Fiordelisio Coll",
    "Tere Almazán Mason",
    "Teresa Antonia Meléndez Victoria",
    "Teresa Beatríz Nava Ramírez",
    "Teresa Becerril Torres",
    "Teresa Fátima Castellanos Hernández",
    "Teresa Ruiz Olvera",
    "Teresita Lucila Luna Zaragoza",
    "Tetis Gisela Camacho Espinoza",
    "Thelma Isabel Arenas Rodríguez",
    "Tiffani Méndez Gónzalez",
    "Tomás Antonio Valencia Pérez",
    "Tonali Blanco Ayala",
    "Tonatihu Valdez Hernández",
    "Tonatiuh Vera Ramos",
    "Tyra Delgadillo Mendoza",
    "Ulises Armando Rayón Pichardo",
    "Ulises Pérez Cendejas",
    "Ulises Rodríguez Domínguez",
    "Ulises Yunuén Rosas López",
    "Ulisses Jesús Gutiérrez Hernández",
    "Uri Nimrod Ramírez Jarquín",
    "Uriel Isaac Ruíz Jacinto",
    "Valente Santiago Vargas",
    "Valente Vázquez Velázquez",
    "Valentina Rascón Barajas",
    "Valeria Montesinos Chica",
    "Valery Rodríguez Hernández",
    "Varenka Martínez Toledo",
    "Verónica Alejandra Rincón Rubio",
    "Verónica Gil López",
    "Verónica López Delgado",
    "Verónica Martínez de la Vega y Mansilla",
    "Verónica Monserrat Rodríguez Sánchez",
    "Verónica Noemí Zepeda Martínez",
    "Vianey Guadalupe Cortes Hernández",
    "Vicenta Sánchez Morales",
    "Vicente Carrión Velázquez",
    "Vicente Ángel Soriano Ramírez",
    "Victor Hugo Almanza Veloz",
    "Victor Humberto Hernández Moya",
    "Victor Manuel Del Castillo Falconi",
    "Victor Manuel Fuentes Olvera",
    "Victor Sebastian Razo Morales",
    "Victor Ulises Lev Contreras Loera",
    "Victoria Alejandra García Ortega",
    "Victoria Guevara González",
    "Vilma Soledad Ardiles Gloria",
    "Vinicio Antonio Gómez Gutiérrez",
    "Violeta Amparo Romero Mayén",
    "Virginia Teodosio Procopio",
    "Viridiana Ponce Juárez",
    "Viviana Escobar Sánchez",
    "Víctor Alfonso Vicente Benítez",
    "Víctor Antonio Mejía Roa",
    "Víctor Emmanuel Hernández López",
    "Víctor Fidel Rodríguez Torres",
    "Víctor Francisco Breña Medina",
    "Víctor Gabriel Elías García",
    "Víctor Germán Mijangos de la Cruz",
    "Víctor Hernández Santamaría",
    "Víctor Hugo Alvarado Becerril",
    "Víctor Hugo Espíndola Castro",
    "Víctor Hugo López Lugo",
    "Víctor Hugo Mendoza Portilla",
    "Víctor Hugo Meza Laguna",
    "Víctor Leonardo Castañeda Rivas",
    "Víctor Manuel Carreón Calderón",
    "Víctor Manuel García Guerrero",
    "Víctor Manuel Guerrero Sosa",
    "Víctor Manuel Lara Camacho",
    "Víctor Manuel Reza Estrada",
    "Víctor Manuel Velázquez Aguilar",
    "Víctor Manuel Ávila Báez",
    "Víctor Mireles Chávez",
    "Víctor Rogelio Hernández Marroquín",
    "Wendy Gabriela Vázquez Jiménez",
    "Wendy Rocío Juárez Pérez",
    "William José Gallardo",
    "Ximena Delgado Villegas",
    "Ximena Estrada Zavaleta",
    "Xochitl Cruz Núñez",
    "Yadira Valdivieso Díaz",
    "Yahir Alejandro Murillo Rodríguez",
    "Yahir Solares Tenorio",
    "Yair Romero López",
    "Yajaida Noraly Velázquez Inzunza",
    "Yajaira García Feria",
    "Yamilka Karenia López Uc",
    "Yaneli Trujillo Varela",
    "Yanink Neried Caro Vega",
    "Yasmin Mitzi Vargas",
    "Yasmin Vázquez Santos",
    "Yeimi Danae Martínez Camacho",
    "Yeny Garay Solis",
    "Yesenia Angélica García Jomaso",
    "Yessica Janeth Pablo Martínez",
    "Yessica Zeltzin Orozco Armenta",
    "Yorgui Santiago Andres",
    "Youssef Sarkis Mobarak",
    "Yunior Frainen Pérez Araujo",
    "Yurguen Hugo Camargo Serafin",
    "Yuri Bonder Grimberg",
    "Yuri Diana Hernández Ibarra",
    "Yuri Nikolaevich Skiba",
    "Yuriria Cortés Poza",
    "Yurixhi Paola Aguilera León",
    "Yury Glebskiy",
    "Zaira Eréndira Rojas García",
    "Zamira Anahí Ávila Valle",
    "Zeltzin Muñoz Juárez",
    "Zenón Cano Santana",
    "Zeus Alberto Valtierra Quintal",
    "Zeus Tlaltecutli Domínguez Vega",
    "Álvaro Chaos Cador",
    "Álvaro Reyes García",
    "Álvaro Ulloa Benítez",
    "Ángel Eduardo Escárcega Mendicuti",
    "Ángel Fernando Soto Pozos",
    "Ángel Manuel Godoy Aguilar",
    "Ángel Mejía Monroy",
    "Ángel Renato Zamudio Malagón",
    "Ángel Sánchez Cecilio",
    "Ángela Victoria Forero Forero"
  ]
}